djangoauthenticator/__init__.py
djangoauthenticator/djangoauthenticator.py
django_authenticator_gdaley-0.1.5a0.dist-info/LICENSE
django_authenticator_gdaley-0.1.5a0.dist-info/METADATA
django_authenticator_gdaley-0.1.5a0.dist-info/WHEEL
django_authenticator_gdaley-0.1.5a0.dist-info/top_level.txt
django_authenticator_gdaley-0.1.5a0.dist-info/RECORD
