Metadata-Version: 2.1
Name: django-authenticator-gdaley
Version: 0.1.5a0
Summary: Authenticate to JupyterHub using an active Django login session
Home-page: https://github.com/Codicy/django-authenticator
Author: Graham Daley
Author-email: gd@codicy.co
License: UNKNOWN
Project-URL: Bug Tracker, https://github.com/Codicy/django-authenticator/issues
Keywords: jupyterhub,django
Platform: UNKNOWN
Classifier: Programming Language :: Python :: 3
Classifier: License :: OSI Approved :: Apache Software License
Classifier: Operating System :: OS Independent
Requires-Python: >=3.6
License-File: LICENSE
Requires-Dist: jupyterhub
Requires-Dist: mysqlclient
